rustgression-0.4.1.dist-info/METADATA
rustgression-0.4.1.dist-info/WHEEL
rustgression-0.4.1.dist-info/licenses/LICENSE
rustgression/__init__.py
rustgression/__init__.pyi
rustgression/regression/__init__.py
rustgression/regression/__init__.pyi
rustgression/regression/_rust_imports.py
rustgression/regression/base.py
rustgression/regression/base.pyi
rustgression/regression/factory.py
rustgression/regression/factory.pyi
rustgression/regression/ols.py
rustgression/regression/ols.pyi
rustgression/regression/tls.py
rustgression/regression/tls.pyi
rustgression/rustgression.cp311-win_amd64.pyd
rustgression-0.4.1.dist-info/RECORD
