Metadata-Version: 2.4
Name: rustgression
Version: 0.4.1
Classifier: Programming Language :: Python :: 3
Classifier: Programming Language :: Python :: 3.11
Classifier: Programming Language :: Rust
Classifier: License :: OSI Approved :: MIT License
Classifier: Operating System :: OS Independent
Classifier: Typing :: Typed
Requires-Dist: numpy>=1.20.0
Requires-Dist: matplotlib>=3.10.1 ; extra == 'examples'
Requires-Dist: scipy>=1.15.2 ; extra == 'examples'
Provides-Extra: examples
License-File: LICENSE
Summary: Fast OLS and TLS regression using Rust backend
Author-email: connect0459 <connect0459@gmail.com>
License-Expression: MIT
Requires-Python: >=3.11
Project-URL: Homepage, https://github.com/connect0459/rustgression
Project-URL: Bug Tracker, https://github.com/connect0459/rustgression/issues
